setup.py
geodatabase_tempfile/__init__.py
geodatabase_tempfile/version.py
geodatabase_tempfile.egg-info/PKG-INFO
geodatabase_tempfile.egg-info/SOURCES.txt
geodatabase_tempfile.egg-info/dependency_links.txt
geodatabase_tempfile.egg-info/top_level.txt