Metadata-Version: 1.0
Name: geodatabase-tempfile
Version: 0.1.0
Summary: A library for managing temporary geodatabases and filenames in arcpy (ArcGIS) scripts
Home-page: https://github.com/ucd-cws/geodatabase_tempfile
Author: Nick Santos
Author-email: nrsantos@ucdavis.edu
License: UNKNOWN
Platform: UNKNOWN
